pypanabi/__init__.py
pypanabi/aws.py
pypanabi/classic_stream.py
pypanabi/extras.py
pypanabi/file.py
pypanabi/hydra_stream.py
pypanabi/legacy_stream.py
pypanabi/logger.py
pypanabi/panamera_stream.py
pypanabi/social.py
pypanabi/spark.py
pypanabi_tools-1.9.83.dist-info/METADATA
pypanabi_tools-1.9.83.dist-info/WHEEL
pypanabi_tools-1.9.83.dist-info/top_level.txt
pypanabi_tools-1.9.83.dist-info/RECORD
