Metadata-Version: 2.1
Name: pypanabi-tools
Version: 1.9.83
Summary: Shared Python functions for OLX Business Intelligence Team
Home-page: UNKNOWN
Author: OLX
Author-email: panamera-bi@olx.com
License: UNKNOWN
Keywords: olx bi panamera
Platform: UNKNOWN
Classifier: Programming Language :: Python :: 2.7
Requires-Dist: ConfigParser
Requires-Dist: findspark
Requires-Dist: boto3
Requires-Dist: psycopg2-binary
Requires-Dist: pymysql
Requires-Dist: sqlparse
Requires-Dist: click
Requires-Dist: ijson
Requires-Dist: logging
Requires-Dist: fastparquet
Requires-Dist: python-dateutil
Requires-Dist: requests
Requires-Dist: urllib3
Requires-Dist: pytz
Requires-Dist: numpy
Requires-Dist: python-jenkins
Requires-Dist: facebook-sdk
